LICENSE
README.md
pyproject.toml
setup.py
galaxie_microgui.egg-info/PKG-INFO
galaxie_microgui.egg-info/SOURCES.txt
galaxie_microgui.egg-info/dependency_links.txt
galaxie_microgui.egg-info/entry_points.txt
galaxie_microgui.egg-info/requires.txt
galaxie_microgui.egg-info/top_level.txt
microGUI/__init__.py
microGUI/__main__.py
microGUI/mainloop.py
microGUI/Widgets/Basic.py
microGUI/Widgets/Container.py
microGUI/Widgets/Label.py
microGUI/Widgets/Timer.py
microGUI/Widgets/Widget.py
microGUI/Widgets/__init__.py
microGUI/Widgets/bargraph.py
microGUI/Widgets/bkgd.py
microGUI/Widgets/calendar.py
microGUI/Widgets/client.py
microGUI/Widgets/clock.py
microGUI/Widgets/compound.py
microGUI/Widgets/disjoint.py
microGUI/Widgets/fontsel.py
microGUI/Widgets/gauge.py
microGUI/Widgets/graphic.py
microGUI/Widgets/group.py
microGUI/Widgets/imagearea.py
microGUI/Widgets/meter.py
microGUI/Widgets/mtrend.py
microGUI/Widgets/oscontainer.py
microGUI/Widgets/pane.py
microGUI/Widgets/panelgroup.py
microGUI/Widgets/printsel.py
microGUI/Widgets/raw.py
microGUI/Widgets/region.py
microGUI/Widgets/scrollarea.py
microGUI/Widgets/separator.py
microGUI/Widgets/trend.py
microGUI/Widgets/updown.py
microGUI/drivers/__init__.py
microGUI/drivers/ncurses.py
tests/test_mainloop.py