Metadata-Version: 2.1
Name: galaxie-microgui
Version: 0.1a1
Summary: The Galaxie microGUI
Author: Tuuux
License: WTFPL
Project-URL: Homepage, https://codeberg.org/rtnp/galaxie-microgui
Project-URL: Issues, https://codeberg.org/rtnp/galaxie-microgui/-/issues
Project-URL: Readthedocs, http://galaxie-microgui.readthedocs.io
Keywords: Galaxie,TUI,POSIX,GUI
Classifier: Environment :: Console
Classifier: License :: Public Domain
Classifier: Topic :: Software Development :: Libraries :: Python Modules
Classifier: Programming Language :: Python
Classifier: Programming Language :: Python :: 3 :: Only
Requires-Python: >=3.0
License-File: LICENSE
Requires-Dist: wheel
Requires-Dist: setuptools
Provides-Extra: tests
Requires-Dist: coverage; extra == "tests"
Requires-Dist: unittest; extra == "tests"
Requires-Dist: discover; extra == "tests"
Requires-Dist: setuptools; extra == "tests"
Requires-Dist: wheel; extra == "tests"
Provides-Extra: doc
Requires-Dist: sphinx-rtd-theme; extra == "doc"
Requires-Dist: sphinxemoji; extra == "doc"
Requires-Dist: sphinx-autoapi; extra == "doc"
Requires-Dist: sphinx-notfound-page; extra == "doc"
